mypy.ini
.venv/ai-services/lib/python3.8/site-packages/alabaster/about.html
.venv/ai-services/lib/python3.8/site-packages/alabaster/donate.html
.venv/ai-services/lib/python3.8/site-packages/alabaster/layout.html
.venv/ai-services/lib/python3.8/site-packages/alabaster/navigation.html
.venv/ai-services/lib/python3.8/site-packages/alabaster/relations.html
.venv/ai-services/lib/python3.8/site-packages/alembic/templates/async/alembic.ini.mako
.venv/ai-services/lib/python3.8/site-packages/alembic/templates/async/script.py.mako
.venv/ai-services/lib/python3.8/site-packages/alembic/templates/generic/alembic.ini.mako
.venv/ai-services/lib/python3.8/site-packages/alembic/templates/generic/script.py.mako
.venv/ai-services/lib/python3.8/site-packages/alembic/templates/multidb/alembic.ini.mako
.venv/ai-services/lib/python3.8/site-packages/alembic/templates/multidb/script.py.mako
.venv/ai-services/lib/python3.8/site-packages/coverage/htmlfiles/index.html
.venv/ai-services/lib/python3.8/site-packages/coverage/htmlfiles/pyfile.html
.venv/ai-services/lib/python3.8/site-packages/docutils-0.18.1.dist-info/SOURCES.html
.venv/ai-services/lib/python3.8/site-packages/docutils-0.18.1.dist-info/dependency_links.html
.venv/ai-services/lib/python3.8/site-packages/docutils-0.18.1.dist-info/top_level.html
.venv/ai-services/lib/python3.8/site-packages/sanic_ext/extensions/openapi/ui/redoc.html
.venv/ai-services/lib/python3.8/site-packages/sanic_ext/extensions/openapi/ui/swagger.html
.venv/ai-services/lib/python3.8/site-packages/sphinx/themes/agogo/layout.html
.venv/ai-services/lib/python3.8/site-packages/sphinx/themes/basic/defindex.html
.venv/ai-services/lib/python3.8/site-packages/sphinx/themes/basic/domainindex.html
.venv/ai-services/lib/python3.8/site-packages/sphinx/themes/basic/genindex-single.html
.venv/ai-services/lib/python3.8/site-packages/sphinx/themes/basic/genindex-split.html
.venv/ai-services/lib/python3.8/site-packages/sphinx/themes/basic/genindex.html
.venv/ai-services/lib/python3.8/site-packages/sphinx/themes/basic/globaltoc.html
.venv/ai-services/lib/python3.8/site-packages/sphinx/themes/basic/layout.html
.venv/ai-services/lib/python3.8/site-packages/sphinx/themes/basic/localtoc.html
ai_services-0.5.5.dist-info/METADATA
ai_services-0.5.5.dist-info/WHEEL
ai_services-0.5.5.dist-info/entry_points.txt
ai_services-0.5.5.dist-info/licenses/LICENSE
ai_services-0.5.5.dist-info/RECORD
