Metadata-Version: 2.1
Name: ai-services
Version: 0.5.5
Summary: "A simple web framework based on Sanic"
Project-URL: Documentation, https://github.com/nuxion/services#readme
Project-URL: Issues, https://github.com/nuxion/services/issues
Project-URL: Source, https://github.com/nuxion/services
Author-email: nuxion <nuxion@gmail.com>
License-Expression: MIT
License-File: LICENSE
Classifier: Development Status :: 4 - Beta
Classifier: Programming Language :: Python
Classifier: Programming Language :: Python :: 3.8
Classifier: Programming Language :: Python :: 3.9
Classifier: Programming Language :: Python :: 3.10
Classifier: Programming Language :: Python :: Implementation :: CPython
Classifier: Programming Language :: Python :: Implementation :: PyPy
Requires-Python: >=3.8
Requires-Dist: aiofiles<23,>=22.1.0
Requires-Dist: click~=8.1.3
Requires-Dist: cryptography>=41.0.1
Requires-Dist: itsdangerous~=2.1.2
Requires-Dist: jinja2>=3.1
Requires-Dist: pydantic~=1.10.7
Requires-Dist: pyjwt>=2.6.0
Requires-Dist: rich>=12
Provides-Extra: docs
Requires-Dist: furo; extra == 'docs'
Requires-Dist: myst-parser; extra == 'docs'
Requires-Dist: sphinx~=5.3.0; extra == 'docs'
Provides-Extra: google
Requires-Dist: google-cloud-storage==2; extra == 'google'
Requires-Dist: smart-open==6; extra == 'google'
Provides-Extra: redis
Requires-Dist: redis~=4.5.1; extra == 'redis'
Provides-Extra: sql
Requires-Dist: alembic>=1.10.3; extra == 'sql'
Requires-Dist: sqlalchemy>=2.0.7; extra == 'sql'
Provides-Extra: web
Requires-Dist: redis~=4.5.1; extra == 'web'
Requires-Dist: sanic-ext~=23.3.0; extra == 'web'
Requires-Dist: sanic~=23.3.0; extra == 'web'
